torchscan/__init__.py
torchscan/crawler.py
torchscan/utils.py
torchscan/version.py
torchscan/modules/__init__.py
torchscan/modules/flops.py
torchscan/modules/macs.py
torchscan/modules/memory.py
torchscan/modules/receptive.py
torchscan/process/__init__.py
torchscan/process/memory.py
torchscan-0.1.2.dist-info/LICENSE
torchscan-0.1.2.dist-info/METADATA
torchscan-0.1.2.dist-info/WHEEL
torchscan-0.1.2.dist-info/top_level.txt
torchscan-0.1.2.dist-info/zip-safe
torchscan-0.1.2.dist-info/RECORD
